{
  "workflowType": "Conditional",

  "task": "Process a customer support ticket: analyze the issue, classify it, route to a technical specialist, and generate a final response.",

  "orchestration": {
    "startAgent": "TicketAnalyzerAgent",
    "edges": [
      { "from": "TicketAnalyzerAgent", "to": "TicketClassifierAgent", "label": "Analysis" },
      { "from": "TicketClassifierAgent", "to": "TechnicalSupportAgent", "label": "Tech Route" },
      { "from": "TechnicalSupportAgent", "to": "ResponseGeneratorAgent", "label": "Resolution" }
    ],
    "conditionalEdges": [
      {
        "from": "TicketClassifierAgent",
        "toOptions": ["TechnicalSupportAgent", "BillingSupportAgent", "GeneralInquiryAgent"],
        "selectionFunction": "classify_ticket_type",
        "parameters": {
          "confidenceThreshold": 0.8,
          "allowMultiple": false
        }
      }
    ]
  },

  "agents": [
    {
      "name": "TicketAnalyzerAgent",
      "description": "Extracts key facts from the customer ticket",
      "instructions": "Read the ticket, extract problem description, sentiment, urgency, and any error messages. Output a structured summary.",
      "modelId": "bjoernb/gemma4-e2b-fast",
      "plugins": ["TimePlugin"],
      "metadata": { "stage": "analysis", "priority": "high" }
    },
    {
      "name": "TicketClassifierAgent",
      "description": "Classifies the ticket category",
      "instructions": "Classify the ticket as 'technical', 'billing', or 'general' with a confidence score.",
      "modelId": "bjoernb/gemma4-e2b-fast",
      "metadata": { "stage": "classification", "decisionMaker": true }
    },
    {
      "name": "TechnicalSupportAgent",
      "description": "Resolves technical issues",
      "instructions": "Diagnose the issue, provide step-by-step troubleshooting, and indicate whether engineering escalation is required.",
      "modelId": "bjoernb/gemma4-e2b-fast",
      "tools": ["CodeInterpreter"],
      "metadata": { "stage": "resolution", "specialization": "technical" }
    },
    {
      "name": "ResponseGeneratorAgent",
      "description": "Composes the customer-facing reply",
      "instructions": "Use the prior agents' outputs to write a concise, empathetic, professional response with clear next steps.",
      "modelId": "bjoernb/gemma4-e2b-fast",
      "metadata": { "stage": "finalization", "priority": "high" }
    }
  ],

  "manager": {
    "modelId": "bjoernb/gemma4-e2b-fast",
    "maxRoundCount": 4,
    "maxStallCount": 2,
    "maxResetCount": 1,
    "enablePlanReview": false
  },

  "settings": {
    "_note": "conditionalEdges.selectionFunction is parsed but not yet executed (deferred). Static edges drive routing in current version."
  }
}
